smsapi/__init__.py
smsapi/api.py
smsapi/auth.py
smsapi/client.py
smsapi/compat.py
smsapi/endpoint.py
smsapi/exception.py
smsapi/models.py
smsapi/utils.py
smsapi/account/__init__.py
smsapi/account/api.py
smsapi/account/models.py
smsapi/blacklist/__init__.py
smsapi/blacklist/api.py
smsapi/blacklist/models.py
smsapi/contacts/__init__.py
smsapi/contacts/api.py
smsapi/contacts/exceptions.py
smsapi/contacts/models.py
smsapi/hlr/__init__.py
smsapi/hlr/api.py
smsapi/mfa/__init__.py
smsapi/mfa/api.py
smsapi/mfa/model.py
smsapi/mms/__init__.py
smsapi/mms/api.py
smsapi/sender/__init__.py
smsapi/sender/api.py
smsapi/sender/models.py
smsapi/short_url/__init__.py
smsapi/short_url/api.py
smsapi/short_url/models.py
smsapi/sms/__init__.py
smsapi/sms/api.py
smsapi/sms/model.py
smsapi/vms/__init__.py
smsapi/vms/api.py
smsapi_client-2.9.6.dist-info/LICENSE
smsapi_client-2.9.6.dist-info/METADATA
smsapi_client-2.9.6.dist-info/WHEEL
smsapi_client-2.9.6.dist-info/top_level.txt
smsapi_client-2.9.6.dist-info/RECORD
