Metadata-Version: 2.1
Name: smsapi-client
Version: 2.9.6
Summary: SmsAPI client
Home-page: https://github.com/smsapi/smsapi-python-client
Author: SMSAPI
Author-email: bok@smsapi.pl
License: UNKNOWN
Platform: UNKNOWN
Classifier: Development Status :: 5 - Production/Stable
Classifier: Intended Audience :: Developers
Classifier: License :: OSI Approved :: Apache Software License
Classifier: Topic :: Software Development :: Libraries :: Python Modules
Classifier: Programming Language :: Python :: 2.7
Classifier: Programming Language :: Python :: 3.4
Classifier: Programming Language :: Python :: 3.5
Classifier: Programming Language :: Python :: 3.6
Classifier: Programming Language :: Python :: 3.7
